radgrafter/__init__.py
radgrafter/rad.py
radgrafter-0.0.4.dist-info/METADATA
radgrafter-0.0.4.dist-info/WHEEL
radgrafter-0.0.4.dist-info/top_level.txt
radgrafter-0.0.4.dist-info/RECORD
