Metadata-Version: 2.1
Name: radgrafter
Version: 0.0.4
Summary: Package for request forwarding.
Home-page: https://github.com/inksong/radgrafter
Author: ink
Author-email: ink@isafetech.cn
License: UNKNOWN
Project-URL: Bug Tracker, https://github.com/inksong/radgrafter/issues
Platform: UNKNOWN
Classifier: Programming Language :: Python :: 2.7
Classifier: License :: OSI Approved :: MIT License
Classifier: Operating System :: OS Independent
Requires-Python: >=2.7
